{
  "configVersion": 1,
  "timestamp": 1689267857799,
  "index": "/portal/index.html",
  "assetGroups": [
    {
      "name": "app",
      "installMode": "prefetch",
      "updateMode": "prefetch",
      "cacheQueryOptions": {
        "ignoreVary": true
      },
      "urls": [
        "/portal/196.9779b0c8c4a5127b.js",
        "/portal/2.35c6c49d321a10e8.js",
        "/portal/233.f10bf220667950f5.js",
        "/portal/268.864a8b34d5ac7542.js",
        "/portal/291.5e1d190ee3271fe4.js",
        "/portal/35.e0301807ef985e7d.js",
        "/portal/361.cd104a41ffe9602d.js",
        "/portal/378.89f9f22fa71fd13d.js",
        "/portal/386.76fb4aa7216d465c.js",
        "/portal/418.751e1f4037e49254.js",
        "/portal/441.afc1f7e00636a358.js",
        "/portal/546.60d9b59196dc238f.js",
        "/portal/629.d1db11530df023c2.js",
        "/portal/671.74472f526f0631d0.js",
        "/portal/676.4d5878f4255bdbf0.js",
        "/portal/759.3e2cc2f7945304bc.js",
        "/portal/805.3f8ed502a897185d.js",
        "/portal/840.039045668a85022b.js",
        "/portal/851.21378d653df3f3c4.js",
        "/portal/896.c132224d9fb6e7cd.js",
        "/portal/911.95b86a0a0713b65d.js",
        "/portal/common.02d85cb85174ed59.js",
        "/portal/favicon.ico",
        "/portal/index.html",
        "/portal/main.15675d42035bb934.js",
        "/portal/manifest.webmanifest",
        "/portal/polyfills.7c978ea6c48a313b.js",
        "/portal/runtime.869139e833e522c1.js",
        "/portal/styles.61e5990be0acdd15.css"
      ],
      "patterns": []
    },
    {
      "name": "assets",
      "installMode": "lazy",
      "updateMode": "prefetch",
      "cacheQueryOptions": {
        "ignoreVary": true
      },
      "urls": [
        "/portal/assets/icons/icon-128x128.png",
        "/portal/assets/icons/icon-144x144.png",
        "/portal/assets/icons/icon-152x152.png",
        "/portal/assets/icons/icon-192x192.png",
        "/portal/assets/icons/icon-384x384.png",
        "/portal/assets/icons/icon-48x48.png",
        "/portal/assets/icons/icon-512x512.png",
        "/portal/assets/icons/icon-72x72.png",
        "/portal/assets/icons/icon-96x96.png",
        "/portal/assets/icons/jam.svg",
        "/portal/assets/icons/manthra.svg",
        "/portal/assets/icons/ordoo.svg",
        "/portal/assets/icons/startup-weekend.svg",
        "/portal/assets/pic/image_2023-05-04_15-36-30.jpg",
        "/portal/assets/pic/jam.webp",
        "/portal/assets/pic/kdz.webp",
        "/portal/assets/pic/tshirtSize.jpg"
      ],
      "patterns": []
    }
  ],
  "dataGroups": [
    {
      "name": "news",
      "patterns": [
        "https:\\/\\/kdz\\.ir\\/fa\\/\\?json=get_posts"
      ],
      "strategy": "freshness",
      "maxSize": 50,
      "maxAge": 86400000,
      "cacheQueryOptions": {
        "ignoreVary": true
      },
      "version": 1
    },
    {
      "name": "sportInsurance",
      "patterns": [
        "https:\\/\\/api\\.kdz\\.ir\\/api\\/v1\\/account\\/jam\\/single\\/sport-insurance"
      ],
      "strategy": "performance",
      "maxSize": 50,
      "maxAge": 5000,
      "cacheQueryOptions": {
        "ignoreVary": true
      },
      "version": 1
    },
    {
      "name": "jam",
      "patterns": [
        "https:\\/\\/api\\.kdz\\.ir\\/api\\/v1\\/account\\/jam\\/can-register"
      ],
      "strategy": "performance",
      "maxSize": 50,
      "maxAge": 300000,
      "cacheQueryOptions": {
        "ignoreVary": true
      },
      "version": 1
    },
    {
      "name": "history",
      "patterns": [
        "https:\\/\\/kdz\\.ir\\/fa\\/\\?json=get_page&id=1036"
      ],
      "strategy": "performance",
      "maxSize": 50,
      "maxAge": 2592000000,
      "cacheQueryOptions": {
        "ignoreVary": true
      },
      "version": 1
    },
    {
      "name": "user-images",
      "patterns": [
        "https:\\/\\/api\\.kdz\\.ir\\/api\\/v1\\/files\\/show\\/.*"
      ],
      "strategy": "performance",
      "maxSize": 100,
      "maxAge": 432000000,
      "cacheQueryOptions": {
        "ignoreVary": true
      },
      "version": 1
    },
    {
      "name": "outer-images",
      "patterns": [
        "https:\\/\\/file\\.behroozbc\\.ir\\/no_logo\\.png"
      ],
      "strategy": "performance",
      "maxSize": 120,
      "maxAge": 4320000000,
      "cacheQueryOptions": {
        "ignoreVary": true
      },
      "version": 1
    }
  ],
  "hashTable": {
    "/portal/196.9779b0c8c4a5127b.js": "1883e7d7f0d2428ddf1e714b9a65c38f8402ec29",
    "/portal/2.35c6c49d321a10e8.js": "0fca491a4b06e939da3362c806b29e6ba2fb5249",
    "/portal/233.f10bf220667950f5.js": "48e30712678d2c6093cb7c12844b0bbfab57e0dc",
    "/portal/268.864a8b34d5ac7542.js": "ff6548b016968816ca95e07ebb38b70d0d421630",
    "/portal/291.5e1d190ee3271fe4.js": "d3bb5ba7a2e36f3809323d68cf2caa8ce96a0e72",
    "/portal/35.e0301807ef985e7d.js": "f75d4c3028b894f3c12b027a8b5681d606732389",
    "/portal/361.cd104a41ffe9602d.js": "aa5cd11bfd8a2c1aebe9dd53453e2231920735c4",
    "/portal/378.89f9f22fa71fd13d.js": "954177a8d55b0eb17162342690d4809e437def8d",
    "/portal/386.76fb4aa7216d465c.js": "8c88a6a78ce8c189284c9fbace8c4e77f1aab781",
    "/portal/418.751e1f4037e49254.js": "67f8e01dc4475028faec3b594e1cc2f92819023b",
    "/portal/441.afc1f7e00636a358.js": "819bbf35b9a26d1beb0f3386538870f4c8d0aab5",
    "/portal/546.60d9b59196dc238f.js": "c758cadc215133f088a6a3cefc67b77d371b943f",
    "/portal/629.d1db11530df023c2.js": "d8d78a23b76103847669202d79ae13e102abf2b2",
    "/portal/671.74472f526f0631d0.js": "aebe43f054536a5e56658d83cf7ad9761012c31f",
    "/portal/676.4d5878f4255bdbf0.js": "afb62c752b6882d9185693ada4886ae0aa424e9b",
    "/portal/759.3e2cc2f7945304bc.js": "86c347f707c881e2aee9f47b9e29ddec4c9a93a0",
    "/portal/805.3f8ed502a897185d.js": "7d33df60b85418a7b7deb62870149235cd6dcafd",
    "/portal/840.039045668a85022b.js": "65b56f2925d38e6c2e111199b419c87cfe36825e",
    "/portal/851.21378d653df3f3c4.js": "be4be6aa4d4910499d56bed407cec14399406c3c",
    "/portal/896.c132224d9fb6e7cd.js": "cbcc2599c1978cc690d3ff7c5fb50131839a0495",
    "/portal/911.95b86a0a0713b65d.js": "82ff89ebbae89cf5eff10ec83d13445729660bcd",
    "/portal/assets/icons/icon-128x128.png": "d7d1222cd9f26a807793a4ed562ad2b5ab83d720",
    "/portal/assets/icons/icon-144x144.png": "249524f48d9f9b411fd7c302f0231204db5cb9bd",
    "/portal/assets/icons/icon-152x152.png": "70df2922f6f9f402b1563e0498e309cd15e8cc7a",
    "/portal/assets/icons/icon-192x192.png": "8ef3087b4596fb61690a9037b39b4171f5b74b18",
    "/portal/assets/icons/icon-384x384.png": "c2b71b6a4995e52dcfa98736fcfec41c654020fc",
    "/portal/assets/icons/icon-48x48.png": "9b4e7344a4d1bf8d15d404a7c47e01ba563fa9dd",
    "/portal/assets/icons/icon-512x512.png": "a765d87f5678dcd9069c98ff37af36959350c344",
    "/portal/assets/icons/icon-72x72.png": "9d3ab01937b093dd75573645916bbd0d14004473",
    "/portal/assets/icons/icon-96x96.png": "d2bfb6987d19a71d88a9d3b1ff44aad3e6b761f8",
    "/portal/assets/icons/jam.svg": "478129edbab9538891f16641bb17f0a04f15c1d3",
    "/portal/assets/icons/manthra.svg": "556cfb31bbd0c2c793993e3ea8024ad8b1be1cb4",
    "/portal/assets/icons/ordoo.svg": "1c82479e3ac394a3c4c85c67c7c7af39599c4295",
    "/portal/assets/icons/startup-weekend.svg": "2de7c21d94d0cf21794e669db11d2fd81cf9571b",
    "/portal/assets/pic/image_2023-05-04_15-36-30.jpg": "d7d93bd41d040478025b95be83d6489ef03342ec",
    "/portal/assets/pic/jam.webp": "845b373e8967c6d0ec52f327e96147229c157185",
    "/portal/assets/pic/kdz.webp": "7d422cc64b498eaf573a76b73f80340968cb0fc6",
    "/portal/assets/pic/tshirtSize.jpg": "b0d73e10ed68dbd8b4d1e3857cd3f52a61d98fa6",
    "/portal/common.02d85cb85174ed59.js": "62492e9aefeebb0114020bd69df0756762717f7d",
    "/portal/favicon.ico": "a008f051369ce7a5c52f6a2011fa32bd4c429c4f",
    "/portal/index.html": "e8caac9bd671d2209f32565b3e4134e199809311",
    "/portal/main.15675d42035bb934.js": "9011da4247e741e62477a5626fa946021b862a87",
    "/portal/manifest.webmanifest": "c494c902771710a5112e95a6e7023c1410b9b8f9",
    "/portal/polyfills.7c978ea6c48a313b.js": "ed2d1dcd7b4eb15a2ab2d5a4ea9de6728b2310e4",
    "/portal/runtime.869139e833e522c1.js": "6c5568a15094a83321bff9d04a5c7e866d41edfd",
    "/portal/styles.61e5990be0acdd15.css": "257c1cb17b485882d2a52a75bf2f04ee91d06c39"
  },
  "navigationUrls": [
    {
      "positive": true,
      "regex": "^\\/.*$"
    },
    {
      "positive": false,
      "regex": "^\\/(?:.+\\/)?[^/]*\\.[^/]*$"
    },
    {
      "positive": false,
      "regex": "^\\/(?:.+\\/)?[^/]*__[^/]*$"
    },
    {
      "positive": false,
      "regex": "^\\/(?:.+\\/)?[^/]*__[^/]*\\/.*$"
    }
  ],
  "navigationRequestStrategy": "performance"
}